to_upper.v
`timescale 1ns / 1ps

module to_upper ( 
    // inputs are 8 bits of each ascii character
    input wire a0, a1, a2, a3, a4, a5, a6, a7,
    output wire a0_out, a1_out, a2_out, a3_out, a4_out, a5_out, a6_out, a7_out
  );

    wire f1, f2, f3; // output the results of each function
    wire is_lowercase; // returns 1 if F passes through

    // Defining function 1: a4'(a0 + a1 + a2 + a3)
    // define wires
    wire f1_w_a4_not; // inverter wires
    wire f1_w_or_gate_1, f1_w_or_gate_2, f1_w_or_gate_3; // output of or gates
    wire f1_w_and_gate_1; // output of and gate

    // define inverter gates
    not #(5) G_f1_not4(f1_w_a4_not, a4);

    // define or/and gates
    or #(10) G_f1_or1(f1_w_or_gate_1, a0, a1);
    or #(10) G_f1_or2(f1_w_or_gate_2, f1_w_or_gate_1, a2);
    or #(10) G_f1_or3(f1_w_or_gate_3, f1_w_or_gate_2, a3);
    and #(10) G_f1_and(f1, f1_w_a4_not, f1_w_or_gate_3); // output function 1


    // Defining function 2: a4(a3' + a3a2'(a1' + a0'))
    // define wires
    wire f2_w_a0_not, f2_w_a1_not, f2_w_a2_not, f2_w_a3_not;
    wire f2_w_or_gate_1, f2_w_or_gate_2;
    wire f2_w_and_gate_1, f2_w_and_gate_2;
    // wire f2_logic_result;

    // define inverter gates
    not #(5) G_f2_not0(f2_w_a0_not, a0);
    not #(5) G_f2_not1(f2_w_a1_not, a1);
    not #(5) G_f2_not2(f2_w_a2_not, a2);
    not #(5) G_f2_not3(f2_w_a3_not, a3);

    // define or/and gates
    or #(10) G_f2_or1(f2_w_or_gate_1, f2_w_a1_not, f2_w_a0_not);
    and #(10) G_f2_and1(f2_w_and_gate_1, f2_w_or_gate_1, f2_w_a2_not);
    or #(10) G_f2_or2(f2_w_or_gate_2, f2_w_and_gate_1, f2_w_a3_not);
    and #(10) G_f2_and2(f2, f2_w_or_gate_2, a4);

    // and #(10) G_f2_and1(f2_w_and_gate_1, f2_w_a2_not, f2_w_or_gate_1);
    // and #(10) G_f2_and2(f2_w_and_gate_2, f2_w_and_gate_1, a3);
    // or #(10) G_f2_or2(f2_logic_result, f2_w_a3_not, f2_w_and_gate_3);
    // and #(10) G_f2_and(f2, a4, f2_logic_result);

    // Defining function 3: a7'a6a5
    // define wires
    wire w_a7_not, w_f3_and;

    // define inverter
    not #(5) G_f3_not7(w_a7_not, a7);   
    // define and gate
    and #(10) G_f3_and1(w_f3_and, a5, a6);
    and #(10) G_f3_and(f3, w_a7_not, w_f3_and);  

    wire f1_or_f2; // connect f1 and f2
    or #(10) G_f2_f1_or(f1_or_f2, f1, f2);

    // connecting F = f1f2f2
    and #(10) G_F_and(is_lowercase, f1_or_f2, f3);

    // Generate output:
    // assign outputs, which are the same for everything besides a5
    assign a0_out = a0;
    assign a1_out = a1;
    assign a2_out = a2;
    assign a3_out = a3;
    assign a4_out = a4;
    assign a6_out = a6;
    assign a7_out = a7;

    wire is_lowercase_not;

    not #(5) G_condition_not(is_lowercase_not, is_lowercase);
    and #(10) G_bit5_logic(a5_out, a5, is_lowercase_not);

endmodule

tb_to_upper.v
// testbank for to_upper function


`timescale 1ns / 1ps


module tb_to_upper;
// declare inputs and outputs
    reg [7:0] test_char;
    wire [7:0] result_char;

    // Initialize device under test
    to_upper dut (
        // Connect output ports of the DUT to bits of the 'result_char' wire
        .a0_out(result_char[0]), .a1_out(result_char[1]), .a2_out(result_char[2]), .a3_out(result_char[3]),
        .a4_out(result_char[4]), .a5_out(result_char[5]), .a6_out(result_char[6]), .a7_out(result_char[7]),

        
        // Connect input ports of the DUT to bits of the 'test_char' reg
        .a0(test_char[0]), .a1(test_char[1]), .a2(test_char[2]), .a3(test_char[3]),
        .a4(test_char[4]), .a5(test_char[5]), .a6(test_char[6]), .a7(test_char[7])
    );

    initial begin
        $dumpfile("to_upper_waveform.vcd");
        $dumpvars(0, tb_to_upper);


        $display("Starting to_upper testbench...");

        $display("After testing multiple delay times, #41 was found to be the correct amount to make the circuit work\n");

        // Test 1 ( dec 40
        test_char = 8'd40;
        //NOTE increase delay (#20) to #41 to check if the propogation delay is correct
        #50;
        $display("Input: %s (%d), Output: %s (%d)", test_char, test_char, result_char, result_char);

        // Test 2 H dec 72
        test_char = 8'd72;
        #41;
        $display("Input: %s (%d), Output: %s (%d)", test_char, test_char, result_char, result_char);

        // Test 3 . dec 183
        test_char = 8'd183;
        #41;
        $display("Input: %s (%d), Output: %s (%d)", test_char, test_char, result_char, result_char);

        // Test 4 ƒ dec 131
        test_char = 8'd131;
        #41;
        $display("Input: %s (%d), Output: %s (%d)", test_char, test_char, result_char, result_char);

        // Test 5 | dec 124
        test_char = 8'd124;
        #41;
        $display("Input: %s (%d), Output: %s (%d)", test_char, test_char, result_char, result_char);

        // Test 6 DC4 dec 20
        test_char = 8'd20;
        #41;
        $display("Input: %s (%d), Output: %s (%d)", test_char, test_char, result_char, result_char);

        // Test 7 ë dec 235
        test_char = 8'd235;
        #41;
        $display("Input: %s (%d), Output: %s (%d)", test_char, test_char, result_char, result_char);

        // Test 8 a dec 97
        test_char = 8'd97;
        #41;
        $display("Input: %s (%d), Output: %s (%d)", test_char, test_char, result_char, result_char);

        // Test 9 A dec 65
        test_char = 8'd65;
        #41;
        $display("Input: %s (%d), Output: %s (%d)", test_char, test_char, result_char, result_char);

        // Test 10 z dec 122
        test_char = 8'd122;
        #41;
        $display("Input: %s (%d), Output: %s (%d)", test_char, test_char, result_char, result_char);

        // Test 11 G dec 71
        test_char = 8'd71;
        #41;
        $display("Input: %s (%d), Output: %s (%d)", test_char, test_char, result_char, result_char);

        // Test 12 m dec 109
        test_char = 8'd109;
        #50;
        $display("Input: %s (%d), Output: %s (%d)", test_char, test_char, result_char, result_char);

        // Test 13 ' dec 146
        test_char = 8'd146;
        #41;
        $display("Input: %s (%d), Output: %s (%d)", test_char, test_char, result_char, result_char);

        // Test 14 ) dec 48
        test_char = 8'd48;
        #41;
        $display("Input: %s (%d), Output: %s (%d)", test_char, test_char, result_char, result_char);

        // Test 15 Ï dec 207
        test_char = 8'd207;
        #41;
        $display("Input: %s (%d), Output: %s (%d)", test_char, test_char, result_char, result_char);

        // Test 16 : dec 58
        test_char = 8'd58;
        #41;
        $display("Input: %s (%d), Output: %s (%d)", test_char, test_char, result_char, result_char);

        // Test 17 { dec 123
        test_char = 8'd123;
        #41;
        $display("Input: %s (%d), Output: %s (%d)", test_char, test_char, result_char, result_char);

        // Test 18 " dec 148
        test_char = 8'd148;
        #41;
        $display("Input: %s (%d), Output: %s (%d)", test_char, test_char, result_char, result_char);

        // Test 19 DEL dec 127
        test_char = 8'd127;
        #41;
        $display("Input: %s (%d), Output: %s (%d)", test_char, test_char, result_char, result_char);

        $display("\nTest finished.");
        $finish;
end

endmodule;

to_upper_waveform.vcd
$date
	Wed Nov  5 15:45:29 2025
$end
$version
	Icarus Verilog
$end
$timescale
	1ps
$end
$scope module tb_to_upper $end
$var wire 8 ! result_char [7:0] $end
$var reg 8 " test_char [7:0] $end
$scope module dut $end
$var wire 1 # a0 $end
$var wire 1 $ a0_out $end
$var wire 1 % a1 $end
$var wire 1 & a1_out $end
$var wire 1 ' a2 $end
$var wire 1 ( a2_out $end
$var wire 1 ) a3 $end
$var wire 1 * a3_out $end
$var wire 1 + a4 $end
$var wire 1 , a4_out $end
$var wire 1 - a5 $end
$var wire 1 . a5_out $end
$var wire 1 / a6 $end
$var wire 1 0 a6_out $end
$var wire 1 1 a7 $end
$var wire 1 2 a7_out $end
$var wire 1 3 f1 $end
$var wire 1 4 f1_or_f2 $end
$var wire 1 5 f1_w_a4_not $end
$var wire 1 6 f1_w_or_gate_1 $end
$var wire 1 7 f1_w_or_gate_2 $end
$var wire 1 8 f1_w_or_gate_3 $end
$var wire 1 9 f2 $end
$var wire 1 : f2_w_a0_not $end
$var wire 1 ; f2_w_a1_not $end
$var wire 1 < f2_w_a2_not $end
$var wire 1 = f2_w_a3_not $end
$var wire 1 > f2_w_and_gate_1 $end
$var wire 1 ? f2_w_or_gate_1 $end
$var wire 1 @ f2_w_or_gate_2 $end
$var wire 1 A f3 $end
$var wire 1 B is_lowercase $end
$var wire 1 C is_lowercase_not $end
$var wire 1 D w_a7_not $end
$var wire 1 E w_f3_and $end
$upscope $end
$upscope $end
$enddefinitions $end
$comment Show the parameter values. $end
$dumpall
$end
#0
$dumpvars
xE
xD
xC
xB
xA
x@
x?
x>
x=
x<
x;
x:
x9
x8
x7
x6
x5
x4
x3
02
01
00
0/
x.
1-
0,
0+
1*
1)
0(
0'
0&
0%
0$
0#
b101000 "
b0x01000 !
$end
#5000
1:
1;
1<
0=
15
1D
#10000
06
18
09
0E
#15000
1?
#20000
07
13
0A
#25000
1>
#30000
14
0B
#35000
1C
1@
#45000
b101000 !
1.
#50000
0-
b1101000 !
10
1/
b1001000 "
#60000
b1001000 !
0.
#91000
1$
1#
1&
1%
1(
1'
0*
0)
1,
1+
1-
00
0/
b10010111 !
12
11
b10110111 "
#96000
0:
0;
0<
1=
05
0D
#101000
16
17
08
19
b10110111 !
1.
#106000
0?
0>
03
#111000
18
#132000
0(
0'
b10100011 !
0,
0+
0-
b10000011 "
#137000
1<
15
#142000
09
b10000011 !
0.
#147000
13
#173000
0$
0#
0&
0%
1(
1'
1*
1)
1,
1+
1-
10
1/
b1011100 !
02
01
b1111100 "
#178000
1:
1;
0<
0=
05
1D
#183000
06
19
b1111100 !
1.
1E
#188000
1?
0@
03
#193000
1A
#198000
09
#203000
1B
#208000
0C
04
#214000
0*
0)
0-
b110100 !
00
0/
b10100 "
#218000
b10100 !
0.
0B
#219000
1=
#223000
1C
#224000
0E
#229000
1@
#234000
0A
#239000
19
#249000
14
#255000
1$
1#
1&
1%
0(
0'
1*
1)
0,
0+
1-
10
1/
b11001011 !
12
11
b11101011 "
#260000
0:
0;
1<
0=
15
0D
#265000
16
07
09
b11101011 !
1.
1E
#270000
0?
1>
0@
13
#275000
17
#280000
0>
1@
#290000
0@
#296000
0&
0%
0*
0)
b1100001 !
02
01
b1100001 "
#301000
1;
1=
1D
#311000
1?
1@
1A
#321000
1>
1B
#326000
0C
#336000
b1000001 !
0.
#337000
0-
b1000001 "
#347000
0E
#357000
0A
#367000
0B
#372000
1C
#378000
0$
0#
1&
1%
1*
1)
b1011010 !
1,
1+
1-
b1111010 "
#383000
1:
0;
0=
05
#388000
19
1E
b1111010 !
1.
#393000
03
#398000
1A
#408000
1B
#413000
0C
#419000
1$
1#
1(
1'
0*
0)
b1100111 !
0,
0+
0-
b1000111 "
#423000
b1000111 !
0.
#424000
0:
0<
1=
15
#429000
09
0E
#434000
0?
0>
13
#439000
0A
#449000
0B
#454000
1C
#460000
0&
0%
b1001101 !
1*
1)
1-
b1101101 "
#465000
1;
0=
#470000
1E
b1101101 !
1.
#475000
1?
0@
#480000
1A
#490000
1B
#495000
0C
#505000
b1001101 !
0.
#510000
0$
0#
1&
1%
0(
0'
0*
0)
1,
1+
0-
00
0/
b10010010 !
12
11
b10010010 "
#515000
1:
0;
1<
1=
05
0D
#520000
0E
#525000
1>
1@
03
0A
#535000
19
04
0B
#540000
1C
#545000
14
#551000
0&
0%
1-
b10000 !
02
01
b110000 "
#556000
1;
1D
#561000
06
b110000 !
1.
#571000
07
#581000
08
#592000
1$
1#
1&
1%
1(
1'
1*
1)
0,
0+
0-
10
1/
b11101111 !
12
11
b11001111 "
#597000
0:
0;
0<
0=
15
0D
#602000
16
17
18
09
b11001111 !
0.
#607000
0?
0>
#612000
13
04
#617000
0@
#622000
14
#633000
0$
0#
0(
0'
1,
1+
1-
00
0/
b11010 !
02
01
b111010 "
#638000
1:
1<
05
1D
#643000
b111010 !
1.
#648000
1?
03
#658000
1>
04
#668000
1@
#674000
1$
1#
b1111011 !
10
1/
b1111011 "
#678000
19
#679000
0:
#684000
1E
#688000
14
#689000
0?
#694000
1A
#699000
0>
#704000
1B
#709000
0C
0@
#715000
0$
0#
0&
0%
1(
1'
0*
0)
0-
00
0/
b10110100 !
12
11
b10010100 "
#719000
b10010100 !
0.
09
#720000
1:
1;
0<
1=
0D
#725000
06
0E
#729000
04
#730000
1?
1@
0A
#739000
0B
#740000
19
#744000
1C
#750000
14
#756000
1$
1#
1&
1%
1*
1)
1-
10
1/
b1011111 !
02
01
b1111111 "
#761000
0:
0;
0=
1D
#766000
16
b1111111 !
1.
1E
#771000
0?
0@
#776000
1A
#781000
09
#786000
1B
#791000
0C
04
