to_upper.v
`timescale 1ns / 1ps

module to_upper ( 
    // inputs are 8 bits of each ascii character
    input wire a0, a1, a2, a3, a4, a5, a6, a7,
    output wire a0_out, a1_out, a2_out, a3_out, a4_out, a5_out, a6_out, a7_out
  );

    wire f1, f2, f3; // output the results of each function
    wire is_lowercase; // returns 1 if F passes through

    // Defining function 1: a4'(a0 + a1 + a2 + a3)
    // define wires
    wire f1_w_a4_not; // inverter wires
    wire f1_w_or_gate_1, f1_w_or_gate_2, f1_w_or_gate_3; // output of or gates
    wire f1_w_and_gate_1; // output of and gate

    // define inverter gates
    not #(5) G_f1_not4(f1_w_a4_not, a4);

    // define or/and gates
    or #(10) G_f1_or1(f1_w_or_gate_1, a0, a1);
    or #(10) G_f1_or2(f1_w_or_gate_2, f1_w_or_gate_1, a2);
    or #(10) G_f1_or3(f1_w_or_gate_3, f1_w_or_gate_2, a3);
    and #(10) G_f1_and(f1, f1_w_a4_not, f1_w_or_gate_3); // output function 1


    // Defining function 2: a4(a3' + a3a2'(a1' + a0'))
    // define wires
    wire f2_w_a0_not, f2_w_a1_not, f2_w_a2_not, f2_w_a3_not;
    wire f2_w_or_gate_1, f2_w_or_gate_2;
    wire f2_w_and_gate_1, f2_w_and_gate_2;
    // wire f2_logic_result;

    // define inverter gates
    not #(5) G_f2_not0(f2_w_a0_not, a0);
    not #(5) G_f2_not1(f2_w_a1_not, a1);
    not #(5) G_f2_not2(f2_w_a2_not, a2);
    not #(5) G_f2_not3(f2_w_a3_not, a3);

    // define or/and gates
    or #(10) G_f2_or1(f2_w_or_gate_1, f2_w_a1_not, f2_w_a0_not);
    and #(10) G_f2_and1(f2_w_and_gate_1, f2_w_or_gate_1, f2_w_a2_not);
    or #(10) G_f2_or2(f2_w_or_gate_2, f2_w_and_gate_1, f2_w_a3_not);
    and #(10) G_f2_and2(f2, f2_w_or_gate_2, a4);

    // and #(10) G_f2_and1(f2_w_and_gate_1, f2_w_a2_not, f2_w_or_gate_1);
    // and #(10) G_f2_and2(f2_w_and_gate_2, f2_w_and_gate_1, a3);
    // or #(10) G_f2_or2(f2_logic_result, f2_w_a3_not, f2_w_and_gate_3);
    // and #(10) G_f2_and(f2, a4, f2_logic_result);

    // Defining function 3: a7'a6a5
    // define wires
    wire w_a7_not, w_f3_and;

    // define inverter
    not #(5) G_f3_not7(w_a7_not, a7);   
    // define and gate
    and #(10) G_f3_and1(w_f3_and, a5, a6);
    and #(10) G_f3_and(f3, w_a7_not, w_f3_and);  

    // connect f1 and f2 with an or gate
    wire f1_or_f2; 
    or #(10) G_f2_f1_or(f1_or_f2, f1, f2);

    // connecting F = f1f2f2 with and gate
    and #(10) G_F_and(is_lowercase, f1_or_f2, f3);

    // Generate output:
    // assign outputs, which are the same for everything besides a5
    assign a0_out = a0;
    assign a1_out = a1;
    assign a2_out = a2;
    assign a3_out = a3;
    assign a4_out = a4;
    assign a6_out = a6;
    assign a7_out = a7;

    wire is_lowercase_not;

    not #(5) G_condition_not(is_lowercase_not, is_lowercase);
    and #(10) G_bit5_logic(a5_out, a5, is_lowercase_not);

endmodule

tb_to_upper.v
// testbank for to_upper function


`timescale 1ns / 1ps


module tb_to_upper;
// declare inputs and outputs
    reg [7:0] test_char;
    wire [7:0] result_char;

    // Initialize device under test
    to_upper dut (
        // Connect output ports of the DUT to bits of the 'result_char' wire
        .a0_out(result_char[0]), .a1_out(result_char[1]), .a2_out(result_char[2]), .a3_out(result_char[3]),
        .a4_out(result_char[4]), .a5_out(result_char[5]), .a6_out(result_char[6]), .a7_out(result_char[7]),

        
        // Connect input ports of the DUT to bits of the 'test_char' reg
        .a0(test_char[0]), .a1(test_char[1]), .a2(test_char[2]), .a3(test_char[3]),
        .a4(test_char[4]), .a5(test_char[5]), .a6(test_char[6]), .a7(test_char[7])
    );

    initial begin
        $dumpfile("to_upper_waveform.vcd");
        $dumpvars(0, tb_to_upper);


        $display("Starting to_upper testbench...");

        // Test 1 ( dec 40
        test_char = 8'd40;
        //TODO increase delay (#20) to #100 to check if the propogation delay is correct
        #100;
        $display("Input: %s (%d), Output: %s (%d)", test_char, test_char, result_char, result_char);

        // Test 2 H dec 72
        test_char = 8'd72;
        #100;
        $display("Input: %s (%d), Output: %s (%d)", test_char, test_char, result_char, result_char);

        // Test 3 . dec 183
        test_char = 8'd183;
        #100;
        $display("Input: %s (%d), Output: %s (%d)", test_char, test_char, result_char, result_char);

        // Test 4 ƒ dec 131
        test_char = 8'd131;
        #100;
        $display("Input: %s (%d), Output: %s (%d)", test_char, test_char, result_char, result_char);

        // Test 5 | dec 124
        test_char = 8'd124;
        #100;
        $display("Input: %s (%d), Output: %s (%d)", test_char, test_char, result_char, result_char);

        // Test 6 DC4 dec 20
        test_char = 8'd20;
        #100;
        $display("Input: %s (%d), Output: %s (%d)", test_char, test_char, result_char, result_char);

        // Test 7 ë dec 235
        test_char = 8'd235;
        #100;
        $display("Input: %s (%d), Output: %s (%d)", test_char, test_char, result_char, result_char);

        // Test 8 a dec 97
        test_char = 8'd97;
        #100;
        $display("Input: %s (%d), Output: %s (%d)", test_char, test_char, result_char, result_char);

        // Test 9 A dec 65
        test_char = 8'd65;
        #100;
        $display("Input: %s (%d), Output: %s (%d)", test_char, test_char, result_char, result_char);

        // Test 10 z dec 122
        test_char = 8'd122;
        #100;
        $display("Input: %s (%d), Output: %s (%d)", test_char, test_char, result_char, result_char);

        // Test 11 G dec 71
        test_char = 8'd71;
        #100;
        $display("Input: %s (%d), Output: %s (%d)", test_char, test_char, result_char, result_char);

        // Test 12 m dec 109
        test_char = 8'd109;
        #100;
        $display("Input: %s (%d), Output: %s (%d)", test_char, test_char, result_char, result_char);

        // Test 13 ' dec 146
        test_char = 8'd146;
        #100;
        $display("Input: %s (%d), Output: %s (%d)", test_char, test_char, result_char, result_char);

        // Test 14 ) dec 48
        test_char = 8'd48;
        #100;
        $display("Input: %s (%d), Output: %s (%d)", test_char, test_char, result_char, result_char);

        // Test 15 Ï dec 207
        test_char = 8'd207;
        #100;
        $display("Input: %s (%d), Output: %s (%d)", test_char, test_char, result_char, result_char);

        // Test 16 : dec 58
        test_char = 8'd58;
        #100;
        $display("Input: %s (%d), Output: %s (%d)", test_char, test_char, result_char, result_char);

        // Test 17 { dec 123
        test_char = 8'd123;
        #100;
        $display("Input: %s (%d), Output: %s (%d)", test_char, test_char, result_char, result_char);

        // Test 18 " dec 148
        test_char = 8'd148;
        #100;
        $display("Input: %s (%d), Output: %s (%d)", test_char, test_char, result_char, result_char);

        // Test 19 DEL dec 127
        test_char = 8'd127;
        #100;
        $display("Input: %s (%d), Output: %s (%d)", test_char, test_char, result_char, result_char);

        $display("Test finished.");
        $finish;
end

endmodule;

to_upper_waveform.vcd
$date
	Wed Nov  5 14:24:14 2025
$end
$version
	Icarus Verilog
$end
$timescale
	1ps
$end
$scope module tb_to_upper $end
$var wire 8 ! result_char [7:0] $end
$var reg 8 " test_char [7:0] $end
$scope module dut $end
$var wire 1 # a0 $end
$var wire 1 $ a0_out $end
$var wire 1 % a1 $end
$var wire 1 & a1_out $end
$var wire 1 ' a2 $end
$var wire 1 ( a2_out $end
$var wire 1 ) a3 $end
$var wire 1 * a3_out $end
$var wire 1 + a4 $end
$var wire 1 , a4_out $end
$var wire 1 - a5 $end
$var wire 1 . a5_out $end
$var wire 1 / a6 $end
$var wire 1 0 a6_out $end
$var wire 1 1 a7 $end
$var wire 1 2 a7_out $end
$var wire 1 3 f1 $end
$var wire 1 4 f1_or_f2 $end
$var wire 1 5 f1_w_a4_not $end
$var wire 1 6 f1_w_or_gate_1 $end
$var wire 1 7 f1_w_or_gate_2 $end
$var wire 1 8 f1_w_or_gate_3 $end
$var wire 1 9 f2 $end
$var wire 1 : f2_w_a0_not $end
$var wire 1 ; f2_w_a1_not $end
$var wire 1 < f2_w_a2_not $end
$var wire 1 = f2_w_a3_not $end
$var wire 1 > f2_w_and_gate_1 $end
$var wire 1 ? f2_w_or_gate_1 $end
$var wire 1 @ f2_w_or_gate_2 $end
$var wire 1 A f3 $end
$var wire 1 B is_lowercase $end
$var wire 1 C is_lowercase_not $end
$var wire 1 D w_a7_not $end
$var wire 1 E w_f3_and $end
$upscope $end
$upscope $end
$enddefinitions $end
$comment Show the parameter values. $end
$dumpall
$end
#0
$dumpvars
xE
xD
xC
xB
xA
x@
x?
x>
x=
x<
x;
x:
x9
x8
x7
x6
x5
x4
x3
02
01
00
0/
x.
1-
0,
0+
1*
1)
0(
0'
0&
0%
0$
0#
b101000 "
b0x01000 !
$end
#5000
1:
1;
1<
0=
15
1D
#10000
06
18
09
0E
#15000
1?
#20000
07
13
0A
#25000
1>
#30000
14
0B
#35000
1C
1@
#45000
b101000 !
1.
#100000
0-
b1101000 !
10
1/
b1001000 "
#110000
b1001000 !
0.
#200000
1$
1#
1&
1%
1(
1'
0*
0)
1,
1+
1-
00
0/
b10010111 !
12
11
b10110111 "
#205000
0:
0;
0<
1=
05
0D
#210000
16
17
08
19
b10110111 !
1.
#215000
0?
0>
03
#220000
18
#300000
0(
0'
b10100011 !
0,
0+
0-
b10000011 "
#305000
1<
15
#310000
09
b10000011 !
0.
#315000
13
#400000
0$
0#
0&
0%
1(
1'
1*
1)
1,
1+
1-
10
1/
b1011100 !
02
01
b1111100 "
#405000
1:
1;
0<
0=
05
1D
#410000
06
19
b1111100 !
1.
1E
#415000
1?
0@
03
#420000
1A
#425000
09
#430000
1B
#435000
0C
04
#445000
b1011100 !
0.
0B
#450000
1C
#460000
b1111100 !
1.
#500000
0*
0)
0-
b110100 !
00
0/
b10100 "
#505000
1=
#510000
b10100 !
0.
0E
#515000
1@
#520000
0A
#525000
19
#535000
14
#600000
1$
1#
1&
1%
0(
0'
1*
1)
0,
0+
1-
10
1/
b11001011 !
12
11
b11101011 "
#605000
0:
0;
1<
0=
15
0D
#610000
16
07
09
b11101011 !
1.
1E
#615000
0?
1>
0@
13
#620000
17
#625000
0>
1@
#635000
0@
#700000
0&
0%
0*
0)
b1100001 !
02
01
b1100001 "
#705000
1;
1=
1D
#715000
1?
1@
1A
#725000
1>
1B
#730000
0C
#740000
b1000001 !
0.
#800000
0-
b1000001 "
#810000
0E
#820000
0A
#830000
0B
#835000
1C
#900000
0$
0#
1&
1%
1*
1)
b1011010 !
1,
1+
1-
b1111010 "
#905000
1:
0;
0=
05
#910000
19
1E
b1111010 !
1.
#915000
03
#920000
1A
#930000
1B
#935000
0C
#945000
b1011010 !
0.
#1000000
1$
1#
1(
1'
0*
0)
b1000111 !
0,
0+
0-
b1000111 "
#1005000
0:
0<
1=
15
#1010000
09
0E
#1015000
0?
0>
13
#1020000
0A
#1030000
0B
#1035000
1C
#1100000
0&
0%
b1001101 !
1*
1)
1-
b1101101 "
#1105000
1;
0=
#1110000
1E
b1101101 !
1.
#1115000
1?
0@
#1120000
1A
#1130000
1B
#1135000
0C
#1145000
b1001101 !
0.
#1200000
0$
0#
1&
1%
0(
0'
0*
0)
1,
1+
0-
00
0/
b10010010 !
12
11
b10010010 "
#1205000
1:
0;
1<
1=
05
0D
#1210000
0E
#1215000
1>
1@
03
0A
#1225000
19
04
0B
#1230000
1C
#1235000
14
#1300000
0&
0%
1-
b10000 !
02
01
b110000 "
#1305000
1;
1D
#1310000
06
b110000 !
1.
#1320000
07
#1330000
08
#1400000
1$
1#
1&
1%
1(
1'
1*
1)
0,
0+
0-
10
1/
b11101111 !
12
11
b11001111 "
#1405000
0:
0;
0<
0=
15
0D
#1410000
16
17
18
09
b11001111 !
0.
#1415000
0?
0>
#1420000
13
04
#1425000
0@
#1430000
14
#1500000
0$
0#
0(
0'
1,
1+
1-
00
0/
b11010 !
02
01
b111010 "
#1505000
1:
1<
05
1D
#1510000
b111010 !
1.
#1515000
1?
03
#1525000
1>
04
#1535000
1@
#1545000
19
#1555000
14
#1600000
1$
1#
b1111011 !
10
1/
b1111011 "
#1605000
0:
#1610000
1E
#1615000
0?
#1620000
1A
#1625000
0>
#1630000
1B
#1635000
0C
0@
#1645000
b1011011 !
0.
09
#1655000
04
#1665000
0B
#1670000
1C
#1680000
b1111011 !
1.
#1700000
0$
0#
0&
0%
1(
1'
0*
0)
0-
00
0/
b10110100 !
12
11
b10010100 "
#1705000
1:
1;
0<
1=
0D
#1710000
06
b10010100 !
0.
0E
#1715000
1?
1@
0A
#1725000
19
#1735000
14
#1800000
1$
1#
1&
1%
1*
1)
1-
10
1/
b1011111 !
02
01
b1111111 "
#1805000
0:
0;
0=
1D
#1810000
16
b1111111 !
1.
1E
#1815000
0?
0@
#1820000
1A
#1825000
09
#1830000
1B
#1835000
0C
04
#1845000
b1011111 !
0.
0B
#1850000
1C
#1860000
b1111111 !
1.
