to_upper.v
`timescale 1ns / 1ps

module to_upper ( 
    // inputs are 8 bits of each ascii character
    input wire a0, a1, a2, a3, a4, a5, a6, a7,
    output wire a0_out, a1_out, a2_out, a3_out, a4_out, a5_out, a6_out, a7_out
  );

    wire f1, f2, f3; // output the results of each function
    wire is_lowercase; // returns 1 if F passes through

    // Defining function 1: a4'(a0 + a1 + a2 + a3)
    // define wires
    wire f1_w_a4_not; // inverter wires
    wire f1_w_or_gate_1, f1_w_or_gate_2, f1_w_or_gate_3; // output of first or gate
    wire f1_w_and_gate_1; // output of first and gate

    // define inverter gates
    not #(5) G_f1_not4(f1_w_a4_not, a4);

    // define or/and gates
    or #(10) G_f1_or1(f1_w_or_gate_1, a0, a1);
    or #(10) G_f1_or2(f1_w_or_gate_2, f1_w_or_gate_1, a2);
    or #(10) G_f1_or3(f1_w_or_gate_3, f1_w_or_gate_3, a3);
    and #(10) G_f1_and(f1, f1_w_a4_not, f1_w_or_gate_3); // output function 1


    // Defining function 2: a4(a3' + a3a2'(a1' + a0'))
    // define wires
    wire f2_w_a0_not, f2_w_a1_not, f2_w_a2_not, f2_w_a3_not;
    wire f2_w_or_gate_2, f2_w_or_gate_3;
    wire f2_w_and_gate_2, f2_w_and_gate_3;
    wire f2_logic_result;

    // define inverter gates
    not #(5) G_f2_not0(f2_w_a0_not, a0);
    not #(5) G_f2_not1(f2_w_a1_not, a1);
    not #(5) G_f2_not2(f2_w_a2_not, a2);
    not #(5) G_f2_not3(f2_w_a3_not, a3);

    // define or/and gates
    or #(10) G_f2_or2(f2_w_or_gate_2, f2_w_a1_not, f2_w_a0_not);
    and #(10) G_f2_and1(f2_w_and_gate_2, f2_w_a2_not, f2_w_or_gate_2);
    and #(10) G_f2_and2(f2_w_and_gate_3, f2_w_and_gate_2, a3);
    or #(10) G_f2_or3(f2_logic_result, f2_w_a3_not, f2_w_and_gate_3);
    and #(10) G_f2_and(f2, a4, f2_logic_result);

    // Defining function 3: a7'a6a5
    // define wires
    wire w_a7_not, w_f3_and;

    // define inverter
    not #(5) G_f3_not7(w_a7_not, a7);   
    // define and gate
    and #(10) G_f3_and1(w_f3_and, a5, a6);
    and #(10) G_f3_and(f3, w_a7_not, w_f3_and);  

    wire f1_or_f2;
    or #(10) G_f2_f1_or(f1_or_f2, f1, f2);

    // connecting F = f1f2f2
    and #(10) G_F_and(is_lowercase, f1_or_f2, f3);

    // Generate output:
    // assign outputs, which are the same for everything besides a5
    assign a0_out = a0;
    assign a1_out = a1;
    assign a2_out = a2;
    assign a3_out = a3;
    assign a4_out = a4;
    assign a6_out = a6;
    assign a7_out = a7;

    wire is_lowercase_not;

    not #(5) G_condition_not(is_lowercase_not, is_lowercase);
    and #(10) G_bit5_logic(a5_out, a5, is_lowercase_not);

endmodule

tb_to_upper.v
// testbank for to_upper function


`timescale 1ns / 1ps


module tb_to_upper;
// declare inputs and outputs
    reg [7:0] test_char;
    wire [7:0] result_char;

    // Initialize device under test
    to_upper dut (
        // Connect output ports of the DUT to bits of the 'result_char' wire
        .a0_out(result_char[0]), .a1_out(result_char[1]), .a2_out(result_char[2]), .a3_out(result_char[3]),
        .a4_out(result_char[4]), .a5_out(result_char[5]), .a6_out(result_char[6]), .a7_out(result_char[7]),

        
        // Connect input ports of the DUT to bits of the 'test_char' reg
        .a0(test_char[0]), .a1(test_char[1]), .a2(test_char[2]), .a3(test_char[3]),
        .a4(test_char[4]), .a5(test_char[5]), .a6(test_char[6]), .a7(test_char[7])
    );

    initial begin
        $dumpfile("to_upper_waveform.vcd");
        $dumpvars(0, tb_to_upper);


        $display("Starting to_upper testbench...");

        // Test 1 ( dec 40
        test_char = 8'd40;
        #20;
        $display("Input: %s (%d), Output: %s (%d)", test_char, test_char, result_char, result_char);

        // Test 2 H dec 72
        test_char = 8'd72;
        #20;
        $display("Input: %s (%d), Output: %s (%d)", test_char, test_char, result_char, result_char);

        // Test 3 . dec 183
        test_char = 8'd183;
        #20;
        $display("Input: %s (%d), Output: %s (%d)", test_char, test_char, result_char, result_char);

        // Test 4 ƒ dec 131
        test_char = 8'd131;
        #20;
        $display("Input: %s (%d), Output: %s (%d)", test_char, test_char, result_char, result_char);

        // Test 5 | dec 124
        test_char = 8'd124;
        #20;
        $display("Input: %s (%d), Output: %s (%d)", test_char, test_char, result_char, result_char);

        // Test 6 DC4 dec 20
        test_char = 8'd20;
        #20;
        $display("Input: %s (%d), Output: %s (%d)", test_char, test_char, result_char, result_char);

        // Test 7 ë dec 235
        test_char = 8'd235;
        #20;
        $display("Input: %s (%d), Output: %s (%d)", test_char, test_char, result_char, result_char);

        // Test 8 a dec 97
        test_char = 8'd97;
        #20;
        $display("Input: %s (%d), Output: %s (%d)", test_char, test_char, result_char, result_char);

        // Test 9 A dec 65
        test_char = 8'd65;
        #20;
        $display("Input: %s (%d), Output: %s (%d)", test_char, test_char, result_char, result_char);

        // Test 10 z dec 122
        test_char = 8'd122;
        #20;
        $display("Input: %s (%d), Output: %s (%d)", test_char, test_char, result_char, result_char);

        // Test 11 G dec 71
        test_char = 8'd71;
        #20;
        $display("Input: %s (%d), Output: %s (%d)", test_char, test_char, result_char, result_char);

        // Test 12 m dec 109
        test_char = 8'd109;
        #20;
        $display("Input: %s (%d), Output: %s (%d)", test_char, test_char, result_char, result_char);

        // Test 13 ' dec 146
        test_char = 8'd146;
        #20;
        $display("Input: %s (%d), Output: %s (%d)", test_char, test_char, result_char, result_char);

        // Test 14 ) dec 48
        test_char = 8'd48;
        #20;
        $display("Input: %s (%d), Output: %s (%d)", test_char, test_char, result_char, result_char);

        // Test 15 Ï dec 207
        test_char = 8'd207;
        #20;
        $display("Input: %s (%d), Output: %s (%d)", test_char, test_char, result_char, result_char);

        // Test 16 : dec 58
        test_char = 8'd58;
        #20;
        $display("Input: %s (%d), Output: %s (%d)", test_char, test_char, result_char, result_char);

        // Test 17 { dec 123
        test_char = 8'd123;
        #20;
        $display("Input: %s (%d), Output: %s (%d)", test_char, test_char, result_char, result_char);

        // Test 18 " dec 148
        test_char = 8'd148;
        #20;
        $display("Input: %s (%d), Output: %s (%d)", test_char, test_char, result_char, result_char);

        // Test 19 DEL dec 127
        test_char = 8'd127;
        #20;
        $display("Input: %s (%d), Output: %s (%d)", test_char, test_char, result_char, result_char);

        $display("Test finished.");
        $finish;
end

endmodule;

to_upper_waveform.vcd
$date
	Tue Nov  4 23:04:53 2025
$end
$version
	Icarus Verilog
$end
$timescale
	1ps
$end
$scope module tb_to_upper $end
$var wire 8 ! result_char [7:0] $end
$var reg 8 " test_char [7:0] $end
$scope module dut $end
$var wire 1 # a0 $end
$var wire 1 $ a0_out $end
$var wire 1 % a1 $end
$var wire 1 & a1_out $end
$var wire 1 ' a2 $end
$var wire 1 ( a2_out $end
$var wire 1 ) a3 $end
$var wire 1 * a3_out $end
$var wire 1 + a4 $end
$var wire 1 , a4_out $end
$var wire 1 - a5 $end
$var wire 1 . a5_out $end
$var wire 1 / a6 $end
$var wire 1 0 a6_out $end
$var wire 1 1 a7 $end
$var wire 1 2 a7_out $end
$var wire 1 3 f1 $end
$var wire 1 4 f1_or_f2 $end
$var wire 1 5 f1_w_a4_not $end
$var wire 1 6 f1_w_or_gate_1 $end
$var wire 1 7 f1_w_or_gate_2 $end
$var wire 1 8 f1_w_or_gate_3 $end
$var wire 1 9 f2 $end
$var wire 1 : f2_logic_result $end
$var wire 1 ; f2_w_a0_not $end
$var wire 1 < f2_w_a1_not $end
$var wire 1 = f2_w_a2_not $end
$var wire 1 > f2_w_a3_not $end
$var wire 1 ? f2_w_and_gate_2 $end
$var wire 1 @ f2_w_and_gate_3 $end
$var wire 1 A f2_w_or_gate_2 $end
$var wire 1 B f3 $end
$var wire 1 C is_lowercase $end
$var wire 1 D is_lowercase_not $end
$var wire 1 E w_a7_not $end
$var wire 1 F w_f3_and $end
$upscope $end
$upscope $end
$enddefinitions $end
$comment Show the parameter values. $end
$dumpall
$end
#0
$dumpvars
xF
xE
xD
xC
xB
xA
x@
x?
x>
x=
x<
x;
x:
x9
x8
x7
x6
x5
x4
x3
02
01
00
0/
x.
1-
0,
0+
1*
1)
0(
0'
0&
0%
0$
0#
b101000 "
b0x01000 !
$end
#5000
1;
1<
1=
0>
15
1E
#10000
06
18
09
0F
#15000
1A
#20000
0-
b1x01000 !
10
1/
07
13
0B
b1001000 "
#25000
1?
#30000
b1001000 !
0.
14
0C
#35000
1D
1@
#40000
1$
1#
1&
1%
1(
1'
0*
0)
1,
1+
1-
00
0/
b10010111 !
12
11
b10110111 "
#45000
0;
0<
0=
1>
05
0E
1:
#50000
16
17
0@
b10110111 !
1.
#55000
0A
0?
03
19
#60000
0(
0'
b10100011 !
0,
0+
0-
b10000011 "
#65000
1=
15
#70000
09
b10000011 !
0.
#75000
13
#80000
0$
0#
0&
0%
1(
1'
1*
1)
1,
1+
1-
10
1/
b1011100 !
02
01
b1111100 "
#85000
1;
1<
0=
0>
05
1E
#90000
06
19
b1111100 !
1.
1F
#95000
1A
0:
03
#100000
0*
0)
0-
b110100 !
00
0/
1B
b10100 "
#105000
1>
09
#110000
b10100 !
0.
0F
1C
#115000
0D
1:
04
#120000
1$
1#
1&
1%
0(
0'
1*
1)
0,
0+
1-
10
1/
b11001011 !
12
11
0B
b11101011 "
#125000
0;
0<
1=
0>
15
0E
0C
#130000
1D
16
07
1F
#135000
0A
1?
0:
13
#140000
0&
0%
0*
0)
02
01
b1100001 !
1.
17
b1100001 "
#145000
1<
1>
1E
0?
14
#155000
1A
1:
1B
#160000
0-
b1000001 "
#165000
1?
1C
#170000
0D
0F
b1000001 !
0.
#180000
0$
0#
1&
1%
1*
1)
b1011010 !
1,
1+
1-
0B
b1111010 "
#185000
1;
0<
0>
05
#190000
1@
19
1F
0C
#195000
1D
03
#200000
1$
1#
1(
1'
0*
0)
b1000111 !
0,
0+
0-
1B
b1000111 "
#205000
0;
0=
1>
15
#210000
0@
09
0F
1C
#215000
0D
0A
0?
13
#220000
0&
0%
b1001101 !
1*
1)
1-
0B
b1101101 "
#225000
1<
0>
#230000
1F
0C
#235000
1D
1A
0:
#240000
0$
0#
1&
1%
0(
0'
0*
0)
1,
1+
0-
00
0/
b10010010 !
12
11
1B
b10010010 "
#245000
1;
0<
1=
1>
05
0E
#250000
0F
1C
#255000
0D
1?
1:
03
0B
#260000
0&
0%
1-
b10000 !
02
01
b110000 "
#265000
1<
1E
19
04
0C
#270000
1D
06
#275000
14
#280000
1$
1#
1&
1%
1(
1'
1*
1)
0,
0+
0-
10
1/
12
11
b11101111 !
1.
07
b11001111 "
#285000
0;
0<
0=
0>
15
0E
#290000
16
17
1@
09
b11001111 !
0.
#295000
0A
0?
13
#300000
0$
0#
0(
0'
1,
1+
1-
00
0/
b11010 !
02
01
b111010 "
#305000
1;
1=
05
1E
0@
#310000
19
b111010 !
1.
#315000
1A
03
0:
#320000
1$
1#
b1111011 !
10
1/
b1111011 "
#325000
0;
1?
09
#330000
1F
#335000
0A
1@
04
#340000
0$
0#
0&
0%
1(
1'
0*
0)
0-
00
0/
b10110100 !
12
11
1B
b10010100 "
#345000
1;
1<
0=
1>
0E
0?
1:
#350000
06
0@
b10010100 !
0.
0F
#355000
1A
0B
19
#360000
1$
1#
1&
1%
1*
1)
1-
10
1/
b1011111 !
02
01
b1111111 "
#365000
0;
0<
0>
1E
14
#370000
16
b1111111 !
1.
1F
#375000
0A
0:
#380000
1B
